kv/sqlite/__init__.py
kv/sqlite/__init__.pyi
kv/sqlite/api.py
kv/sqlite/queries.py
kv_sqlite_sync-0.1.13.dist-info/METADATA
kv_sqlite_sync-0.1.13.dist-info/WHEEL
kv_sqlite_sync-0.1.13.dist-info/top_level.txt
kv_sqlite_sync-0.1.13.dist-info/RECORD
