Metadata-Version: 2.1
Name: kv-sqlite-sync
Version: 0.1.13
Summary: Key-Value interface over SQLite. Supports any datatype, including JSON and BLOB
Author-email: Marcel Claramunt <marcel@moveread.com>
Project-URL: repo, https://github.com/marciclabas/python-storage
Project-URL: home, https://github.com/marciclabas/python-storage/tree/main/kv/kv-sqlite-sync
Requires-Python: >=3.10
Requires-Dist: kv-api
Requires-Dist: haskellian
Requires-Dist: lazy-loader
Requires-Dist: typing-extensions
